{"duck_base_name": "3-RED BASE", "duck_beak_name": "2-LIPSTICK BEAK", "duck_eyes_name": "1-CRYING EYE", "duck_hats_name": "2-RASTA HAT", "duck_outfit_name": "1-YELLOW HOODIE", "duck_base_roll": 3004, "duck_beak_roll": 12407, "duck_eyes_roll": 49224, "duck_hats_roll": 11119, "duck_outfit_roll": 26811, "duck_base_rarity_tier": "4%", "duck_beak_rarity_tier": "25%", "duck_eyes_rarity_tier": "60%", "duck_hats_rarity_tier": "25%", "duck_outfit_rarity_tier": "60%", "duck_base_occurrence_chance": "1.33%", "duck_beak_occurrence_chance": "2.78%", "duck_eyes_occurrence_chance": "7.50%", "duck_hats_occurrence_chance": "2.78%", "duck_outfit_occurrence_chance": "8.57%"}